atombrew/__init__.py
atombrew/__version.py
atombrew/_home.py
atombrew/analysis/__init__.py
atombrew/analysis/_msd.py
atombrew/analysis/RDF/__init__.py
atombrew/analysis/RDF/_rdf_home.py
atombrew/analysis/RDF/_rdf_np.py
atombrew/analysis/RDF/_rdfinterface.py
atombrew/chemistry/__init__.py
atombrew/chemistry/_molecule.py
atombrew/chemistry/elements/__init__.py
atombrew/chemistry/elements/_color.py
atombrew/chemistry/elements/_mass.py
atombrew/cli/__init__.py
atombrew/cli/_main.py
atombrew/cli/_trjconvert.py
atombrew/io/__init__.py
atombrew/io/_trjopener.py
atombrew/io/_trjopenerinterface.py
atombrew/io/_trjwriter.py
atombrew/io/_trjwriterinterface.py
atombrew/io/fmt/__init__.py
atombrew/io/fmt/gromacs/__init__.py
atombrew/io/fmt/gromacs/groopener.py
atombrew/io/fmt/lammps/__init__.py
atombrew/io/fmt/lammps/lammpstrjopener.py
atombrew/io/fmt/lammps/lmpsopener.py
atombrew/io/fmt/lammps/lmpswriter.py
atombrew/io/fmt/pdb/__init__.py
atombrew/io/fmt/pdb/pdbopener.py
atombrew/io/fmt/vasp/__init__.py
atombrew/io/fmt/vasp/poscaropener.py
atombrew/io/fmt/vasp/poscarwriter.py
atombrew/io/fmt/xyz/__init__.py
atombrew/io/fmt/xyz/extxyzopener.py
atombrew/io/fmt/xyz/extxyzwriter.py
atombrew/io/fmt/xyz/xyzopener.py
atombrew/io/fmt/xyz/xyzwriter.py
atombrew/space/__init__.py
atombrew/space/_boundary.py
atombrew/space/_calculate.py
atombrew/space/_kdtree.py
atombrew-0.0.9.dist-info/LICENSE
atombrew-0.0.9.dist-info/METADATA
atombrew-0.0.9.dist-info/WHEEL
atombrew-0.0.9.dist-info/entry_points.txt
atombrew-0.0.9.dist-info/top_level.txt
atombrew-0.0.9.dist-info/zip-safe
atombrew-0.0.9.dist-info/RECORD
