Metadata-Version: 2.1
Name: atombrew
Version: 0.0.9
Summary: Package for post-processing the trajectory files of MD.
Home-page: https://github.com/minu928/atombrew
Author: Knu
Author-email: minu928@snu.ac.kr
Requires-Python: >=3.9
License-File: LICENSE
Requires-Dist: numpy <2.0.0,>=1.22.3
Requires-Dist: tqdm >=4.66.4
Requires-Dist: scipy >=1.11.4
Requires-Dist: pandas >=2.1.4
